{"images":[{"startdate":"20200627","fullstartdate":"202006270700","enddate":"20200628","url":"/th?id=OHR.MtBaldoSantuario_EN-US6460114986_1920x1080.jpg&rf=LaDigue_1920x1080.jpg&pid=hp","urlbase":"/th?id=OHR.MtBaldoSantuario_EN-US6460114986","copyright":"The Sanctuary of Madonna della Corona in Italy (© Volodymyr Kalyniuk/Alamy)","copyrightlink":"https://www.bing.com/search?q=Santuario+Madonna+della+Corona&form=hpcapt&filters=HpDate%3a%2220200627_0700%22","title":"Looking for peace on the precipice","quiz":"/search?q=Bing+homepage+quiz&filters=WQOskey:%22HPQuiz_20200627_MtBaldoSantuario%22&FORM=HPQUIZ","wp":true,"hsh":"3173b8d04c850d8638f9c5a2883d01ec","drk":1,"top":1,"bot":1,"hs":[]}],"tooltips":{"loading":"Loading...","previous":"Previous image","next":"Next image","walle":"This image is not available to download as wallpaper.","walls":"Download this image. Use of this image is restricted to wallpaper only."}}