{"images":[{"startdate":"20200704","fullstartdate":"202007040700","enddate":"20200705","url":"/th?id=OHR.DCFireworksVideo_EN-US7892229177_1920x1080.jpg&rf=LaDigue_1920x1080.jpg&pid=hp","urlbase":"/th?id=OHR.DCFireworksVideo_EN-US7892229177","copyright":"Independence Day fireworks over the National Mall, Washington, DC (© Jon Bilous/Shutterstock)","copyrightlink":"https://www.bing.com/search?q=fourth+of+july&form=hpcapt&filters=HpDate%3a%2220200704_0700%22","title":"Happy Independence Day!","quiz":"/search?q=Bing+homepage+quiz&filters=WQOskey:%22HPQuiz_20200704_DCFireworksVideo%22&FORM=HPQUIZ","wp":false,"hsh":"1934e6fda198431449518963eb8b6b87","drk":1,"top":1,"bot":1,"hs":[]}],"tooltips":{"loading":"Loading...","previous":"Previous image","next":"Next image","walle":"This image is not available to download as wallpaper.","walls":"Download this image. Use of this image is restricted to wallpaper only."}}