{"images":[{"startdate":"20200626","fullstartdate":"202006260700","enddate":"20200627","url":"/th?id=OHR.AdansoniaGrandidieri_EN-US6269745972_1920x1080.jpg&rf=LaDigue_1920x1080.jpg&pid=hp","urlbase":"/th?id=OHR.AdansoniaGrandidieri_EN-US6269745972","copyright":"Grandidier's baobab forest near Morondava, Madagascar (© Thomas Marent/Minden Pictures)","copyrightlink":"https://www.bing.com/search?q=madagascar+independence+day&form=hpcapt&filters=HpDate%3a%2220200626_0700%22","title":"Beautiful baobabs","quiz":"/search?q=Bing+homepage+quiz&filters=WQOskey:%22HPQuiz_20200626_AdansoniaGrandidieri%22&FORM=HPQUIZ","wp":true,"hsh":"0234dc503a834bc906611c5901f664f1","drk":1,"top":1,"bot":1,"hs":[]}],"tooltips":{"loading":"Loading...","previous":"Previous image","next":"Next image","walle":"This image is not available to download as wallpaper.","walls":"Download this image. Use of this image is restricted to wallpaper only."}}