{"images":[{"startdate":"20220326","fullstartdate":"202203260700","enddate":"20220327","url":"/th?id=OHR.YellowCrocuses_EN-US9416168776_1920x1080.jpg&rf=LaDigue_1920x1080.jpg&pid=hp","urlbase":"/th?id=OHR.YellowCrocuses_EN-US9416168776","copyright":"Great tit and yellow crocuses (© Nataba/Getty Images)","copyrightlink":"https://www.bing.com/search?q=crocus&form=hpcapt&filters=HpDate%3a%2220220326_0700%22","title":"Spring awakens","quiz":"/search?q=Bing+homepage+quiz&filters=WQOskey:%22HPQuiz_20220326_YellowCrocuses%22&FORM=HPQUIZ","wp":true,"hsh":"eedc768bab634ee735b80e36ba193e35","drk":1,"top":1,"bot":1,"hs":[]}],"tooltips":{"loading":"Loading...","previous":"Previous image","next":"Next image","walle":"This image is not available to download as wallpaper.","walls":"Download this image. Use of this image is restricted to wallpaper only."}}