{"images":[{"startdate":"20220214","fullstartdate":"202202140800","enddate":"20220215","url":"/th?id=OHR.MaldivesHeart_EN-US7219773610_1920x1080.jpg&rf=LaDigue_1920x1080.jpg&pid=hp","urlbase":"/th?id=OHR.MaldivesHeart_EN-US7219773610","copyright":"Heart-shaped island with sandy beach, offshore coral reef, Indian Ocean, Maldives (© Willyam Bradberry/Shutterstock)","copyrightlink":"https://www.bing.com/search?q=valentine%27s+day&FORM=hpcapt&filters=HpDate%3a%2220220214_0800%22","title":"A Valentine in the Arabian Sea","quiz":"/search?q=Bing+homepage+quiz&filters=WQOskey:%22HPQuiz_20220214_MaldivesHeart%22&FORM=HPQUIZ","wp":true,"hsh":"fae98606393cb24a9d08a420d6f12785","drk":1,"top":1,"bot":1,"hs":[]}],"tooltips":{"loading":"Loading...","previous":"Previous image","next":"Next image","walle":"This image is not available to download as wallpaper.","walls":"Download this image. Use of this image is restricted to wallpaper only."}}