{"images":[{"startdate":"20221129","fullstartdate":"202211290800","enddate":"20221130","url":"/th?id=OHR.HeronGiving_EN-US9774285216_1920x1080.jpg&rf=LaDigue_1920x1080.jpg&pid=hp","urlbase":"/th?id=OHR.HeronGiving_EN-US9774285216","copyright":"Great blue herons building a nest in Wakodahatchee Wetlands, Delray Beach, Florida (© Imagebroker/Alamy)","copyrightlink":"https://www.bing.com/search?q=giving+tuesday&form=hpcapt&filters=HpDate%3a%2220221129_0800%22","title":"A day for giving","quiz":"/search?q=Bing+homepage+quiz&filters=WQOskey:%22HPQuiz_20221129_HeronGiving%22&FORM=HPQUIZ","wp":true,"hsh":"d113d81f469c96bda2d895cfd32e31d2","drk":1,"top":1,"bot":1,"hs":[]}],"tooltips":{"loading":"Loading...","previous":"Previous image","next":"Next image","walle":"This image is not available to download as wallpaper.","walls":"Download this image. Use of this image is restricted to wallpaper only."}}