{"images":[{"startdate":"20230613","fullstartdate":"202306130700","enddate":"20230614","url":"/th?id=OHR.OkefenokeeSwamp_EN-US8688169198_1920x1080.jpg&rf=LaDigue_1920x1080.jpg&pid=hp","urlbase":"/th?id=OHR.OkefenokeeSwamp_EN-US8688169198","copyright":"Trees with Spanish moss over a boardwalk in the Okefenokee Swamp, Folkston, Georgia (© Emmer Photo/Alamy)","copyrightlink":"https://www.bing.com/search?q=Okefenokee+National+Wildlife+Refuge&form=hpcapt&filters=HpDate%3a%2220230613_0700%22","title":"Into the swamp","quiz":"/search?q=Bing+homepage+quiz&filters=WQOskey:%22HPQuiz_20230613_OkefenokeeSwamp%22&FORM=HPQUIZ","wp":true,"hsh":"dfa60530a150beaf783d3746db5fae95","drk":1,"top":1,"bot":1,"hs":[]}],"tooltips":{"loading":"Loading...","previous":"Previous image","next":"Next image","walle":"This image is not available to download as wallpaper.","walls":"Download this image. Use of this image is restricted to wallpaper only."}}