{"images":[{"startdate":"20230818","fullstartdate":"202308180700","enddate":"20230819","url":"/th?id=OHR.AvatarMountain_EN-US0084042494_1920x1080.jpg&rf=LaDigue_1920x1080.jpg&pid=hp","urlbase":"/th?id=OHR.AvatarMountain_EN-US0084042494","copyright":"'Avatar Mountains,' Zhangjiajie National Forest Park, China (© Amazing Aerial Premium/Shutterstock)","copyrightlink":"https://www.bing.com/search?q=Zhangjiajie+National+Forest+Park&form=hpcapt&filters=HpDate%3a%2220230818_0700%22","title":"Inspiring spires of stone","quiz":"/search?q=Bing+homepage+quiz&filters=WQOskey:%22HPQuiz_20230818_AvatarMountain%22&FORM=HPQUIZ","wp":true,"hsh":"5b80278d7c39ee156268a2cbbc08208b","drk":1,"top":1,"bot":1,"hs":[]}],"tooltips":{"loading":"Loading...","previous":"Previous image","next":"Next image","walle":"This image is not available to download as wallpaper.","walls":"Download this image. Use of this image is restricted to wallpaper only."}}