{"images":[{"startdate":"20230115","fullstartdate":"202301150800","enddate":"20230116","url":"/th?id=OHR.Turku_EN-US1258814703_1920x1080.jpg&rf=LaDigue_1920x1080.jpg&pid=hp","urlbase":"/th?id=OHR.Turku_EN-US1258814703","copyright":"Aura River in Turku, Finland (© Jarmo Piironen/Alamy)","copyrightlink":"https://www.bing.com/search?q=Aura+River&form=hpcapt&filters=HpDate%3a%2220230115_0800%22","title":"Frosty Finland","quiz":"/search?q=Bing+homepage+quiz&filters=WQOskey:%22HPQuiz_20230115_Turku%22&FORM=HPQUIZ","wp":true,"hsh":"7ac6249e9422df381d8e064251118cc4","drk":1,"top":1,"bot":1,"hs":[]}],"tooltips":{"loading":"Loading...","previous":"Previous image","next":"Next image","walle":"This image is not available to download as wallpaper.","walls":"Download this image. Use of this image is restricted to wallpaper only."}}