{"images":[{"startdate":"20230808","fullstartdate":"202308080700","enddate":"20230809","url":"/th?id=OHR.InfinityTaipei_EN-US3008697284_1920x1080.jpg&rf=LaDigue_1920x1080.jpg&pid=hp","urlbase":"/th?id=OHR.InfinityTaipei_EN-US3008697284","copyright":"Highways in Taipei, Taiwan (© Tavarius/Shutterstock)","copyrightlink":"https://www.bing.com/search?q=taipei+city&form=hpcapt&filters=HpDate%3a%2220230808_0700%22","title":"To the infinite and back","quiz":"/search?q=Bing+homepage+quiz&filters=WQOskey:%22HPQuiz_20230808_InfinityTaipei%22&FORM=HPQUIZ","wp":true,"hsh":"6961aeffa7e331059b8ed94f9d8be2ef","drk":1,"top":1,"bot":1,"hs":[]}],"tooltips":{"loading":"Loading...","previous":"Previous image","next":"Next image","walle":"This image is not available to download as wallpaper.","walls":"Download this image. Use of this image is restricted to wallpaper only."}}