{"images":[{"startdate":"20231114","fullstartdate":"202311140800","enddate":"20231115","url":"/th?id=OHR.RussellLupines_EN-US8017518812_1920x1080.jpg&rf=LaDigue_1920x1080.jpg&pid=hp","urlbase":"/th?id=OHR.RussellLupines_EN-US8017518812","copyright":"Russell lupines along Lake Tekapo, South Island, New Zealand (© Jeffrey Lewis/Tandem Stills + Motion)","copyrightlink":"https://www.bing.com/search?q=Lupinus&form=hpcapt&filters=HpDate%3a%2220231114_0800%22","title":"A beautiful nuisance","quiz":"/search?q=Bing+homepage+quiz&filters=WQOskey:%22HPQuiz_20231114_RussellLupines%22&FORM=HPQUIZ","wp":true,"hsh":"46788c6f2b2b0cb8fd2765f322524655","drk":1,"top":1,"bot":1,"hs":[]}],"tooltips":{"loading":"Loading...","previous":"Previous image","next":"Next image","walle":"This image is not available to download as wallpaper.","walls":"Download this image. Use of this image is restricted to wallpaper only."}}