{"images":[{"startdate":"20240504","fullstartdate":"202405040700","enddate":"20240505","url":"/th?id=OHR.JediMonastery_EN-US9398447907_1920x1080.jpg&rf=LaDigue_1920x1080.jpg&pid=hp","urlbase":"/th?id=OHR.JediMonastery_EN-US9398447907","copyright":"Ruins of an ancient monastery on the island of Skellig Michael, Ireland (© MNStudio/Getty Images)","copyrightlink":"https://www.bing.com/search?q=Star+Wars+Day&form=hpcapt&filters=HpDate%3a%2220240504_0700%22","title":"May the Fourth be with you!","quiz":"/search?q=Bing+homepage+quiz&filters=WQOskey:%22HPQuiz_20240504_JediMonastery%22&FORM=HPQUIZ","wp":true,"hsh":"606ff54b1d6c852b2982b30474424299","drk":1,"top":1,"bot":1,"hs":[]}],"tooltips":{"loading":"Loading...","previous":"Previous image","next":"Next image","walle":"This image is not available to download as wallpaper.","walls":"Download this image. Use of this image is restricted to wallpaper only."}}