{"images":[{"startdate":"20240728","fullstartdate":"202407280700","enddate":"20240729","url":"/th?id=OHR.BeachHutsSweden_EN-US6029381108_1920x1080.jpg&rf=LaDigue_1920x1080.jpg&pid=hp","urlbase":"/th?id=OHR.BeachHutsSweden_EN-US6029381108","copyright":"Bathing huts on the beach in Skåne County, Sweden (© Martin Wahlborg/Getty Images)","copyrightlink":"https://www.bing.com/search?q=Skane+County+Sweden&form=hpcapt&filters=HpDate%3a%2220240728_0700%22","title":"Chromatic coastline","quiz":"/search?q=Bing+homepage+quiz&filters=WQOskey:%22HPQuiz_20240728_BeachHutsSweden%22&FORM=HPQUIZ","wp":true,"hsh":"1f16aee0f31bcc7f163ed4a197cfe166","drk":1,"top":1,"bot":1,"hs":[]}],"tooltips":{"loading":"Loading...","previous":"Previous image","next":"Next image","walle":"This image is not available to download as wallpaper.","walls":"Download this image. Use of this image is restricted to wallpaper only."}}