{"images":[{"startdate":"20250723","fullstartdate":"202507230700","enddate":"20250724","url":"/th?id=OHR.VaticanCity_EN-US5915643866_1920x1080.jpg&rf=LaDigue_1920x1080.jpg&pid=hp","urlbase":"/th?id=OHR.VaticanCity_EN-US5915643866","copyright":"Vatican City with St. Peter's Basilica (© RudyBalasko/Getty Images)","copyrightlink":"https://www.bing.com/search?q=Vatican+City&form=hpcapt&filters=HpDate%3a%2220250723_0700%22","title":"A country within a city","quiz":"/search?q=Bing+homepage+quiz&filters=WQOskey:%22HPQuiz_20250723_VaticanCity%22&FORM=HPQUIZ","wp":true,"hsh":"3f8abc11072c2ca03c49299b29f92621","drk":1,"top":1,"bot":1,"hs":[]}],"tooltips":{"loading":"Loading...","previous":"Previous image","next":"Next image","walle":"This image is not available to download as wallpaper.","walls":"Download this image. Use of this image is restricted to wallpaper only."}}