{"images":[{"startdate":"20250517","fullstartdate":"202505170700","enddate":"20250518","url":"/th?id=OHR.VeniceLagoon_EN-US3686079353_1920x1080.jpg&rf=LaDigue_1920x1080.jpg&pid=hp","urlbase":"/th?id=OHR.VeniceLagoon_EN-US3686079353","copyright":"A delta in the Venetian Lagoon, Italy (© Dimitri Weber/Amazing Aerial Agency)","copyrightlink":"https://www.bing.com/search?q=Venetian+Lagoon&form=hpcapt&filters=HpDate%3a%2220250517_0700%22","title":"The Venetian 'dolce vita'","quiz":"/search?q=Bing+homepage+quiz&filters=WQOskey:%22HPQuiz_20250517_VeniceLagoon%22&FORM=HPQUIZ","wp":true,"hsh":"a25ee7ed8cd284675e2da84967884788","drk":1,"top":1,"bot":1,"hs":[]}],"tooltips":{"loading":"Loading...","previous":"Previous image","next":"Next image","walle":"This image is not available to download as wallpaper.","walls":"Download this image. Use of this image is restricted to wallpaper only."}}