{"images":[{"startdate":"20250610","fullstartdate":"202506100700","enddate":"20250611","url":"/th?id=OHR.AerialEverglades_EN-US9045585896_1920x1080.jpg&rf=LaDigue_1920x1080.jpg&pid=hp","urlbase":"/th?id=OHR.AerialEverglades_EN-US9045585896","copyright":"Aerial view of Everglades National Park, Florida (© Robert DelVecchio - OcuDrone/Getty Images)","copyrightlink":"https://www.bing.com/search?q=Everglades+National+Park+Florida&form=hpcapt&filters=HpDate%3a%2220250610_0700%22","title":"A river of grass","quiz":"/search?q=Bing+homepage+quiz&filters=WQOskey:%22HPQuiz_20250610_AerialEverglades%22&FORM=HPQUIZ","wp":true,"hsh":"675d6e32ca3e9a4233b1f6ec106f6be6","drk":1,"top":1,"bot":1,"hs":[]}],"tooltips":{"loading":"Loading...","previous":"Previous image","next":"Next image","walle":"This image is not available to download as wallpaper.","walls":"Download this image. Use of this image is restricted to wallpaper only."}}