{"images":[{"startdate":"20250212","fullstartdate":"202502120800","enddate":"20250213","url":"/th?id=OHR.GalapagosIguana_EN-US6976814194_1920x1080.jpg&rf=LaDigue_1920x1080.jpg&pid=hp","urlbase":"/th?id=OHR.GalapagosIguana_EN-US6976814194","copyright":"Marine iguanas, Galápagos Islands, Ecuador (© helovi/Getty Images)","copyrightlink":"https://www.bing.com/search?q=Darwin+Day&form=hpcapt&filters=HpDate%3a%2220250212_0800%22","title":"Darwin's blueprint","quiz":"/search?q=Bing+homepage+quiz&filters=WQOskey:%22HPQuiz_20250212_GalapagosIguana%22&FORM=HPQUIZ","wp":true,"hsh":"28cafda853d1f92fc0bb335b576aa2e9","drk":1,"top":1,"bot":1,"hs":[]}],"tooltips":{"loading":"Loading...","previous":"Previous image","next":"Next image","walle":"This image is not available to download as wallpaper.","walls":"Download this image. Use of this image is restricted to wallpaper only."}}