{"images":[{"startdate":"20260624","fullstartdate":"202606240700","enddate":"20260625","url":"/th?id=OHR.BFPollin_EN-US6519187095_1920x1080.jpg&rf=LaDigue_1920x1080.jpg&pid=hp","urlbase":"/th?id=OHR.BFPollin_EN-US6519187095","copyright":"Butterfly pollinating on yellow flower (© lzh/Getty Images)","copyrightlink":"https://www.bing.com/search?q=pollinator+week&form=hpcapt&filters=HpDate%3a%2220260624_0700%22","title":"Pollen meets wings","quiz":"/search?q=Bing+homepage+quiz&filters=WQOskey:%22HPQuiz_20260624_BFPollin%22&FORM=HPQUIZ","wp":true,"hsh":"92c4b2e886fa39bdc12858e8f0042cfe","drk":1,"top":1,"bot":1,"hs":[]}],"tooltips":{"loading":"Loading...","previous":"Previous image","next":"Next image","walle":"This image is not available to download as wallpaper.","walls":"Download this image. Use of this image is restricted to wallpaper only."}}